[
    {
        "name": "Encriptador de texto v0.0.2",
        "image": "assets/svg/html.svg",
        "link": "https://asdjkl-key.github.io/encryptatorV2/"
    },
    {
        "name":"Encriptador de texto v0.0.1",
        "image":"assets/svg/html.svg",
        "link": "https://asdjkl-key.github.io/challengeone2/"
    },
    {
        "name":"Encriptador de texto v0.0.1",
        "image":"assets/svg/html.svg",
        "link": "https://asdjkl-key.github.io/challengeone2/"
    },
    {
        "name":"Encriptador de texto v0.0.1",
        "image":"assets/svg/html.svg",
        "link": "https://asdjkl-key.github.io/challengeone2/"
    },
    {
        "name":"Encriptador de texto v0.0.1",
        "image":"assets/svg/html.svg",
        "link": "https://asdjkl-key.github.io/challengeone2/"
    },
    {
        "name":"Encriptador de texto v0.0.1",
        "image":"assets/svg/html.svg",
        "link": "https://asdjkl-key.github.io/challengeone2/"
    },
    {
        "name":"Encriptador de texto v0.0.1",
        "image":"assets/svg/html.svg",
        "link": "https://asdjkl-key.github.io/challengeone2/"
    },
    {
        "name":"Encriptador de texto v0.0.1",
        "image":"assets/svg/html.svg",
        "link": "https://asdjkl-key.github.io/challengeone2/"
    },
    {
        "name":"Encriptador de texto v0.0.1",
        "image":"assets/svg/html.svg",
        "link": "https://asdjkl-key.github.io/challengeone2/"
    },
    {
        "name":"Encriptador de texto v0.0.1",
        "image":"assets/svg/html.svg",
        "link": "https://asdjkl-key.github.io/challengeone2/"
    },
    {
        "name":"Encriptador de texto v0.0.1",
        "image":"assets/svg/html.svg",
        "link": "https://asdjkl-key.github.io/challengeone2/"
    }
]